{
  "source_filename": "paternity_leave_act.pdf",
  "title": "Paternity Leave Act",
  "law_number": "R.A. No. 8187",
  "category": "republic_act",
  "pages": [
    {
      "page": 1,
      "text": "ConstitutionStatutesExecutive IssuancesJudicial IssuancesOther IssuancesJurisprudenceInternational Legal ResourcesLegal Links\nToday is Friday, July 10, 2026\nTenth Congress\n[ REPUBLIC ACT NO. 8187, June 11, 1996 ]\nAN ACT GRANTING PATERNITY LEAVE OF SEVEN (7) DAYS WITH FULL PAY TO ALL MARRIED MALEEMPLOYEES IN THE PRIVATE AND PUBLIC SECTORS FOR THE FIRST FOUR (4) DELIVERIES OF THELEGITIMATE SPOUSE WITH WHOM HE IS COHABITING AND FOR OTHER PURPOSES\nBe it enacted by the Senate and House of Representatives of the Philippines in Congress assembled:\nSection 1. Short Title. – This Act shall be known as the \"Paternity Leave Act of 1996.\"\nSection 2. Notwithstanding any law, rules and regulations to the contrary, every married male employee in theprivate and public sectors shall be entitled to a paternity leave of seven (7) days with full pay for the first four (4)deliveries of the legitimate spouse with whom he is cohabiting. The male employee applying for paternity leave shallnotify his employer of the pregnancy of his legitimate spouse and the expected date of such delivery. For purposesof this Act, delivery shall include childbirth or any miscarriage.\nSection 3. Definition of Term. – For purpose of this Act, Paternity Leave refers to the benefits granted to a marriedmale employee allowing him not to report for work for seven (7) days but continues to earn the compensationtherefor, on the condition that his spouse has delivered a child or suffered a miscarriage for purposes of enablinghim to effectively lend support to his wife in her period of recovery and/or in the nursing of the newly-born child.1aшphi1\nSection 4. The Secretary of Labor and Employment, the Chairman of the Civil Service Commission and theSecretary of Health shall, within thirty (30) days from the effectivity of this Act, issue such rules and regulationsnecessary for the proper implementation of the provisions hereof.\nSection 5. Any person, corporation, trust, firm, partnership, association or entity found violating this Act or the rulesand regulations promulgated thereunder shall be punished by a fine not exceeding Twenty-five thousand pesos(P25,000) or imprisonment of not less than thirty (30) days nor more than six (6) months. If the violation iscommitted by a corporation, trust or firm, partnership, association or any other entity, the penalty of imprisonmentshall be imposed on the entity's responsible officers, including, but not limited to, the president, vice-president, chiefexecutive officer, general manager, managing director or partner directly responsible therefor.\nSection 6. Nondiminution Clause. – Nothing in this Act shall be construed to reduce any existing benefits of anyform granted under existing laws, decrees, executive orders, or any contract, agreement or policy between employerand employee.\nSection 7. Repealing Clause. – All laws, ordinances, rules, regulations, issuances, or parts thereof which areinconsistent with this Act are hereby repealed or modified accordingly.\nSection 8. Effectivity. – This Act shall take effect fifteen (15) days from its publication in the Official Gazette or in atleast two (2) newspapers of national circulation.\nApproved, June 11, 1996.\nThe Lawphil Project - Arellano Law Foundation\n7/10/26, 9:59 AM Republic Act No. 8187\nhttps://lawphil.net/statutes/repacts/ra1996/ra_8187_1996.html 1/1",
      "char_count": 3351
    }
  ]
}